evremixes/__init__.py
evremixes/analytics.py
evremixes/analytics_viewer.py
evremixes/config.py
evremixes/main.py
evremixes/menu_helper.py
evremixes/metadata_helper.py
evremixes/track_downloader.py
evremixes/types.py
evremixes-1.0.13.dist-info/METADATA
evremixes-1.0.13.dist-info/WHEEL
evremixes-1.0.13.dist-info/entry_points.txt
evremixes-1.0.13.dist-info/licenses/LICENSE
evremixes-1.0.13.dist-info/RECORD
