Metadata-Version: 2.4
Name: evremixes
Version: 1.0.13
Summary: Evanescence Remix Downloader
License-Expression: MIT
License-File: LICENSE
Author: Danny Stewart
Author-email: danny@stewart.cc
Requires-Python: >=3.12,<4.0
Classifier: Development Status :: 5 - Production/Stable
Classifier: Environment :: Console
Classifier: Intended Audience :: End Users/Desktop
Classifier: License :: OSI Approved :: MIT License
Classifier: Programming Language :: Python :: 3
Classifier: Programming Language :: Python :: 3.12
Classifier: Programming Language :: Python :: 3.13
Classifier: Topic :: Artistic Software
Classifier: Topic :: Internet
Classifier: Topic :: Multimedia
Classifier: Topic :: Multimedia :: Sound/Audio
Classifier: Topic :: Multimedia :: Sound/Audio :: Conversion
Requires-Dist: halo (>=0.0.31)
Requires-Dist: inquirer (>=3.4.1,<4.0.0)
Requires-Dist: mutagen (>=1.47.0,<2.0.0)
Requires-Dist: pillow (>=12.0.0,<13.0.0)
Requires-Dist: polykit (>=0.14.6)
Requires-Dist: requests (>=2.32.5,<3.0.0)
Requires-Dist: types-requests (>=2.32.4.20250913,<3.0.0.0)
Requires-Dist: urllib3 (>=2.6.0,<3.0.0)
Project-URL: Homepage, https://music.dannystewart.com/evanescence/
Project-URL: Repository, https://github.com/dannystewart/evremixes/
